skillshare_downloader/__init__.py
skillshare_downloader/__main__.py
skillshare_downloader/main.py
skillshare_downloader/progress.py
skillshare_downloader/skillshare.py
skillshare_downloader-0.2.2.dist-info/LICENSE
skillshare_downloader-0.2.2.dist-info/METADATA
skillshare_downloader-0.2.2.dist-info/WHEEL
skillshare_downloader-0.2.2.dist-info/entry_points.txt
skillshare_downloader-0.2.2.dist-info/RECORD
