Metadata-Version: 2.1
Name: skillshare-downloader
Version: 0.2.2
Summary: A Python package to download Skillshare classes.
License: MIT
Author: Uriel Albarran Oropeza
Author-email: hello@ozonostudio.com
Requires-Python: >=3.6,<4.0
Classifier: License :: OSI Approved :: MIT License
Classifier: Programming Language :: Python :: 3
Classifier: Programming Language :: Python :: 3.6
Classifier: Programming Language :: Python :: 3.7
Classifier: Programming Language :: Python :: 3.8
Classifier: Programming Language :: Python :: 3.9
Classifier: Programming Language :: Python :: 3.10
Classifier: Programming Language :: Python :: 3.11
Requires-Dist: ffmpeg-python (>=0.2.0,<0.3.0)
Requires-Dist: requests (>=2.26.0,<3.0.0)
Requires-Dist: slugify (>=0.0.1,<0.0.2)
Requires-Dist: telethon (>=1.23.0,<2.0.0)
Requires-Dist: tqdm (>=4.62.2,<5.0.0)
